underwood/__init__.py
underwood/blog.py
underwood/config.py
underwood/feed.py
underwood/file.py
underwood/keys.py
underwood/page.py
underwood/schema.py
underwood/section.py
underwood-0.0.8.dist-info/METADATA
underwood-0.0.8.dist-info/WHEEL
underwood-0.0.8.dist-info/licenses/LICENSE
underwood-0.0.8.dist-info/RECORD
