Metadata-Version: 2.1
Name: underwood
Version: 0.0.8
Summary: Static blog generator
Project-URL: Homepage, https://github.com/liammulh/underwood
Project-URL: Bug Tracker, https://github.com/liammulh/underwood/issues
Author-email: Liam Mulhall <liammulh@gmail.com>
License-File: LICENSE
Classifier: License :: OSI Approved :: MIT License
Classifier: Operating System :: OS Independent
Classifier: Programming Language :: Python :: 3
Requires-Python: >=3.11.4
Requires-Dist: jsonschema>=4.19
